mal_toolbox-2.0.0.dist-info/licenses/AUTHORS
mal_toolbox-2.0.0.dist-info/licenses/LICENSE
maltoolbox/__init__.py
maltoolbox/__main__.py
maltoolbox/exceptions.py
maltoolbox/file_utils.py
maltoolbox/model.py
maltoolbox/py.typed
maltoolbox/str_utils.py
maltoolbox/attackgraph/__init__.py
maltoolbox/attackgraph/attackgraph.py
maltoolbox/attackgraph/node.py
maltoolbox/attackgraph/analyzers/__init__.py
maltoolbox/language/__init__.py
maltoolbox/language/languagegraph.py
maltoolbox/language/compiler/__init__.py
maltoolbox/language/compiler/distributions.py
maltoolbox/language/compiler/exceptions.py
maltoolbox/language/compiler/lang.py
maltoolbox/language/compiler/mal_analyzer.py
maltoolbox/language/compiler/mal_compiler.py
maltoolbox/patternfinder/__init__.py
maltoolbox/patternfinder/attackgraph_patterns.py
maltoolbox/translators/__init__.py
maltoolbox/translators/networkx.py
maltoolbox/translators/updater.py
maltoolbox/visualization/__init__.py
maltoolbox/visualization/draw_io_utils.py
maltoolbox/visualization/graphviz_utils.py
maltoolbox/visualization/neo4j_utils.py
maltoolbox/visualization/utils.py
mal_toolbox-2.0.0.dist-info/METADATA
mal_toolbox-2.0.0.dist-info/WHEEL
mal_toolbox-2.0.0.dist-info/entry_points.txt
mal_toolbox-2.0.0.dist-info/top_level.txt
mal_toolbox-2.0.0.dist-info/RECORD
