Metadata-Version: 2.4
Name: mal-toolbox
Version: 2.0.0
Summary: A collection of tools used to create MAL models and attack graphs.
Author-email: Andrei Buhaiu <buhaiu@kth.se>, Joakim Loxdal <loxdal@kth.se>, Nikolaos Kakouros <nkak@kth.se>, Jakob Nyberg <jaknyb@kth.se>, Giuseppe Nebbione <nebbione@kth.se>, Sandor Berglund <sandor@kth.se>
License: Apache Software License
Project-URL: Homepage, https://github.com/mal-lang/mal-toolbox
Project-URL: Bug Tracker, https://github.com/mal-lang/mal-toolbox/issues
Project-URL: Repository, https://github.com/mal-lang/mal-toolbox
Keywords: mal
Classifier: Development Status :: 3 - Alpha
Classifier: Intended Audience :: Science/Research
Classifier: Programming Language :: Python :: 3
Classifier: License :: OSI Approved :: Apache Software License
Classifier: Operating System :: OS Independent
Classifier: Topic :: Scientific/Engineering
Requires-Python: >=3.10
License-File: LICENSE
License-File: AUTHORS
Requires-Dist: graphviz
Requires-Dist: antlr4-tools
Requires-Dist: antlr4-python3-runtime
Requires-Dist: docopt
Requires-Dist: PyYAML
Requires-Dist: py2neo
Requires-Dist: networkx
Requires-Dist: tree-sitter-mal~=1.0.0
Requires-Dist: tree-sitter
Provides-Extra: dev
Requires-Dist: pytest; extra == "dev"
Dynamic: license-file
